siglost_utils/__init__.py
siglost_utils/api/__init__.py
siglost_utils/api/api.py
siglost_utils/display/__init__.py
siglost_utils/display/display.py
siglost_utils/inference/__init__.py
siglost_utils/inference/inference.py
siglost_utils/utils/__init__.py
siglost_utils/utils/extras.py
siglost_utils/utils/log_events.py
tests/__init__.py
tests/test_display.py
siglost_utils-0.2.3.dist-info/LICENSE
siglost_utils-0.2.3.dist-info/METADATA
siglost_utils-0.2.3.dist-info/WHEEL
siglost_utils-0.2.3.dist-info/top_level.txt
siglost_utils-0.2.3.dist-info/RECORD
