Metadata-Version: 2.1
Name: siglost_utils
Version: 0.2.3
Summary: Python utility package
Home-page: https://github.com/siglost/python_utils
Author: SIGLOST
Author-email: SIGLOST@email.com
License: MIT
Classifier: Programming Language :: Python :: 3
Classifier: Programming Language :: Python :: 3.6
Classifier: Programming Language :: Python :: 3.7
Classifier: Programming Language :: Python :: 3.8
Classifier: License :: OSI Approved :: MIT License
Classifier: Operating System :: OS Independent
Requires-Python: >=3.6
License-File: LICENSE
